<package name="aug" dir="augctx">

  <quotincl>augctx/mpool.h</quotincl>

  <anglincl>stdarg.h</anglincl>
  <interface name="log">

    <method name="vwrite" type="int">
      <param name="level" type="int"/>
      <param name="format" type="const char*"/>
      <param name="args" type="va_list"/>
    </method>

  </interface>

  <verbatim>
/**
 * Create a standard logger.
 *
 * @param mpool The memory pool from which memory will be allocated.
 *
 * @return An interface to the newly created log, or NULL on error.
 */

AUGCTX_API aug_log*
aug_createstdlog(aug_mpool* mpool);
  </verbatim>

</package>
